testcontainers/postgres/__init__.py
tests/test_postgres.py
testcontainers_postgres-0.0.1rc1.dist-info/METADATA
testcontainers_postgres-0.0.1rc1.dist-info/WHEEL
testcontainers_postgres-0.0.1rc1.dist-info/top_level.txt
testcontainers_postgres-0.0.1rc1.dist-info/RECORD
